motivashian/__init__.py
motivashian/doitnow.mkv
motivashian/doitnow.mp3
motivashian-0.1.1.dist-info/LICENSE
motivashian-0.1.1.dist-info/METADATA
motivashian-0.1.1.dist-info/WHEEL
motivashian-0.1.1.dist-info/top_level.txt
motivashian-0.1.1.dist-info/RECORD
