Metadata-Version: 2.1
Name: motivashian
Version: 0.1.1
Summary: Stay motivated
Home-page: UNKNOWN
Author: Arnaud
Author-email: leprogramme.yt@gmail.com
License: MIT
Platform: UNKNOWN
Classifier: Programming Language :: Python :: 3
Classifier: License :: OSI Approved :: MIT License
Classifier: Operating System :: OS Independent
Requires-Dist: imageio
Requires-Dist: imageio-ffmpeg
Requires-Dist: mss
Requires-Dist: pillow
Requires-Dist: numpy
Requires-Dist: playsound
